{
  "label": "조직 평판",
  "mapping": {
    "description": "system.description"
  },
  "entries": {
    "Alluring": {
      "name": "매혹적임",
      "description": ""
    },
    "Ambitious": {
      "name": "야심 많음",
      "description": ""
    },
    "Brutal": {
      "name": "잔인함",
      "description": ""
    },
    "Cruel": {
      "name": "잔혹함",
      "description": ""
    },
    "Daring": {
      "name": "대담함",
      "description": ""
    },
    "Ferocious": {
      "name": "사나움",
      "description": ""
    },
    "Honorable": {
      "name": "명예로움",
      "description": ""
    },
    "Monstrous": {
      "name": "흉포함",
      "description": ""
    },
    "Professional": {
      "name": "프로다움",
      "description": ""
    },
    "Radiant": {
      "name": "빛남",
      "description": ""
    },
    "Savvy": {
      "name": "영리함",
      "description": ""
    },
    "Serene": {
      "name": "차분함",
      "description": ""
    },
    "Sinister": {
      "name": "사악함",
      "description": ""
    },
    "Strange": {
      "name": "괴상함",
      "description": ""
    },
    "Subtle": {
      "name": "미묘함",
      "description": ""
    },
    "Transcendent": {
      "name": "초월적임",
      "description": ""
    }
  }
}